gpx2mesh/__init__.py
gpx2mesh/elevation/__init__.py
gpx2mesh/elevation/test_filenames.py
gpx2mesh/elevation/sources/__init__.py
gpx2mesh/elevation/sources/test_folder_provider.py
gpx2mesh/elevation/sources/test_nasa_provider.py
gpx2mesh/mesh/__init__.py
gpx2mesh/mesh/elevation.py
gpx2mesh/mesh/medal.py
gpx2mesh/mesh/track.py
gpx2mesh/track/__init__.py
gpx2mesh/track/test_track.py
gpx2mesh-0.1.4.dist-info/METADATA
gpx2mesh-0.1.4.dist-info/WHEEL
gpx2mesh-0.1.4.dist-info/RECORD
