Metadata-Version: 2.4
Name: gpx2mesh
Version: 0.1.4
Summary: Add your description here
Requires-Python: >=3.13
Requires-Dist: ipympl>=0.9.7
Requires-Dist: matplotlib>=3.10.3
Requires-Dist: python-dotenv>=1.1.1
Requires-Dist: requests>=2.32.4
Requires-Dist: scipy>=1.15.3
Requires-Dist: trimesh[easy]>=4.6.11
